django_sync_env/__init__.py
django_sync_env/apps.py
django_sync_env/checks.py
django_sync_env/constants.py
django_sync_env/db/__init__.py
django_sync_env/db/base.py
django_sync_env/db/exceptions.py
django_sync_env/db/mongodb.py
django_sync_env/db/mysql.py
django_sync_env/db/postgresql.py
django_sync_env/db/sqlite.py
django_sync_env/log.py
django_sync_env/management/__init__.py
django_sync_env/management/commands/__init__.py
django_sync_env/management/commands/_base.py
django_sync_env/management/commands/sync_env_backup_db.py
django_sync_env/management/commands/sync_env_backup_media.py
django_sync_env/management/commands/sync_env_download_db.py
django_sync_env/management/commands/sync_env_list_db_backups.py
django_sync_env/management/commands/sync_env_list_media_backups.py
django_sync_env/management/commands/sync_env_restore_db.py
django_sync_env/management/commands/sync_env_restore_media.py
django_sync_env/notifications.py
django_sync_env/settings.py
django_sync_env/storage.py
django_sync_env/tasks.py
django_sync_env/utils.py
django_sync_env-1.0.1.dist-info/METADATA
django_sync_env-1.0.1.dist-info/WHEEL
django_sync_env-1.0.1.dist-info/RECORD
