Metadata-Version: 2.4
Name: django-sync-env
Version: 1.0.1
Summary: Backup, Sync and Restore Databases and Media
Author: Dan Brosnan
Author-email: dan.brosnan@octave.nz
Requires-Python: >=3.10,<4.0
Classifier: Framework :: Django
Classifier: Framework :: Django :: 4.2
Classifier: Framework :: Django :: 5.0
Classifier: Framework :: Django :: 5.1
Classifier: Framework :: Django :: 5.2
Classifier: Intended Audience :: Developers
Classifier: Operating System :: OS Independent
Classifier: Programming Language :: Python :: 3
Classifier: Programming Language :: Python :: 3.10
Classifier: Programming Language :: Python :: 3.11
Classifier: Programming Language :: Python :: 3.12
Classifier: Programming Language :: Python :: 3.13
Classifier: Programming Language :: Python :: 3.14
Requires-Dist: aiohttp (>=3.9.5,<4.0.0)
Requires-Dist: django (>=4.2)
Requires-Dist: django-storages (>=1.14.2,<2.0.0)
Requires-Dist: inquirer (>=3.2.4,<4.0.0)
Requires-Dist: slack-sdk (>=3.27.0,<4.0.0)
